django_postgresql_setrole27-1.0.10.dist-info/DESCRIPTION.rst
django_postgresql_setrole27-1.0.10.dist-info/METADATA
django_postgresql_setrole27-1.0.10.dist-info/RECORD
django_postgresql_setrole27-1.0.10.dist-info/WHEEL
django_postgresql_setrole27-1.0.10.dist-info/metadata.json
django_postgresql_setrole27-1.0.10.dist-info/top_level.txt
postgresql_setrole27/__init__.py
