Metadata-Version: 2.0
Name: django-postgresql-setrole27
Version: 1.0.10
Summary: Execute SET ROLE on every PostgreSQL connection in the Django ORM
Home-page: https://github.com/jdelic/django-postgresql-setrole/
Author: GoPythonGo.com
Author-email: info@gopythongo.com
License: UNKNOWN
Platform: UNKNOWN
Classifier: Development Status :: 5 - Production/Stable
Classifier: Intended Audience :: Developers
Classifier: Intended Audience :: System Administrators
Classifier: Programming Language :: Python :: 3 :: Only
Classifier: License :: OSI Approved :: BSD License
Classifier: Operating System :: POSIX
